LICENSE.txt
MANIFEST.in
README.rst
requirements.txt
setup.py
choppy/__init__.py
choppy/chop.py
choppy/choppy.py
choppy/crypto.py
choppy/merge.py
choppy/partition.py
choppy/user_options.py
choppy/util.py
choppy/version.py
choppy.egg-info/PKG-INFO
choppy.egg-info/SOURCES.txt
choppy.egg-info/dependency_links.txt
choppy.egg-info/entry_points.txt
choppy.egg-info/requires.txt
choppy.egg-info/top_level.txt
dev/__init__.py
dev/choppy.py
dev/crypt.py
dev/crypto_02.py
dev/hex_worx.py
dev/tmpdir_test.py
dev/user_args_test.py
dev/util.py
docs/usage.md