Metadata-Version: 1.2
Name: choppy
Version: 0.0.5
Summary: Partition, encrypt, decrypt, and reassemble files.
Home-page: https://github.com/j4c0bs/choppy
Author: Jeremy Jacobs
Author-email: pub@j4c0bs.net
License: BSD
Keywords: cryptography partition
Platform: UNKNOWN
Classifier: Environment :: Console
Classifier: Intended Audience :: Developers
Classifier: Intended Audience :: End Users/Desktop
Classifier: Intended Audience :: Information Technology
Classifier: Intended Audience :: Science/Research
Classifier: License :: OSI Approved :: BSD License
Classifier: Operating System :: OS Independent
Classifier: Programming Language :: Python :: 3.6
Classifier: Topic :: Communications :: File Sharing
Classifier: Topic :: Security :: Cryptography
Classifier: Topic :: Utilities
Requires-Python: >3.6
